Sharesight/SharesightAPI.py
Sharesight/__init__.py
Sharesight-1.0.0.dist-info/METADATA
Sharesight-1.0.0.dist-info/WHEEL
Sharesight-1.0.0.dist-info/top_level.txt
Sharesight-1.0.0.dist-info/RECORD
